<?xml version="1.0" encoding="utf-8"?>
<xliff xmlns="urn:oasis:names:tc:xliff:document:1.2" xmlns:xsi="http://www.w3.org/2001/XMLSchema-instance" version="1.2" xsi:schemaLocation="urn:oasis:names:tc:xliff:document:1.2 xliff-core-1.2-transitional.xsd">
  <file datatype="xml" original="ICodeGenerator.xml" source-language="en-US" target-language="es-ES">
    <header>
      <tool tool-id="mdxliff" tool-name="mdxliff" tool-version="1.0-15c36f0" tool-company="Microsoft" />
      <xliffext:skl_file_name xmlns:xliffext="urn:microsoft:content:schema:xliffextensions">02cd5861-7ce2-4a82-b358-31f8435a0ac5a62cf45342cf364312410c62ff1b11c2674bf1c9.skl</xliffext:skl_file_name>
      <xliffext:version xmlns:xliffext="urn:microsoft:content:schema:xliffextensions">1.2</xliffext:version>
      <xliffext:ms.openlocfilehash xmlns:xliffext="urn:microsoft:content:schema:xliffextensions">a62cf45342cf364312410c62ff1b11c2674bf1c9</xliffext:ms.openlocfilehash>
      <xliffext:ms.sourcegitcommit xmlns:xliffext="urn:microsoft:content:schema:xliffextensions">d31dc2ede16f6f7bc64e90d9f897ff54c4e3869b</xliffext:ms.sourcegitcommit>
      <xliffext:ms.lasthandoff xmlns:xliffext="urn:microsoft:content:schema:xliffextensions">04/03/2018</xliffext:ms.lasthandoff>
      <xliffext:moniker_ids xmlns:xliffext="urn:microsoft:content:schema:xliffextensions">netcore-2.0,netframework-4.5.1,netframework-4.5.2,netframework-4.5,netframework-4.6.1,netframework-4.6.2,netframework-4.6,netframework-4.7.1,netframework-4.7,xamarinmac-3.0</xliffext:moniker_ids>
    </header>
    <body>
      <group id="content" extype="content">
        <trans-unit id="101" translate="yes" xml:space="preserve" uid="T:System.CodeDom.Compiler.ICodeGenerator">
          <source>Defines an interface for generating code.</source>
          <target state="translated">Define una interfaz para generar código.</target>       </trans-unit>
        <trans-unit id="102" translate="yes" xml:space="preserve" extradata="MT" uid="T:System.CodeDom.Compiler.ICodeGenerator">
          <source>In the .NET Framework versions 1.0 and 1.1, code providers consist of implementations of <ph id="ph1">&lt;xref:System.CodeDom.Compiler.CodeDomProvider&gt;</ph>, <ph id="ph2">&lt;xref:System.CodeDom.Compiler.ICodeGenerator&gt;</ph>, <ph id="ph3">&lt;xref:System.CodeDom.Compiler.ICodeParser&gt;</ph>, and <ph id="ph4">&lt;xref:System.CodeDom.Compiler.ICodeCompiler&gt;</ph>.</source>
          <target state="translated">En las versiones 1.0 y 1.1 de .NET Framework, los proveedores de código están formados por implementaciones de <ph id="ph1">&lt;xref:System.CodeDom.Compiler.CodeDomProvider&gt;</ph>, <ph id="ph2">&lt;xref:System.CodeDom.Compiler.ICodeGenerator&gt;</ph>, <ph id="ph3">&lt;xref:System.CodeDom.Compiler.ICodeParser&gt;</ph>, y <ph id="ph4">&lt;xref:System.CodeDom.Compiler.ICodeCompiler&gt;</ph>.</target>       </trans-unit>
        <trans-unit id="103" translate="yes" xml:space="preserve" extradata="MT" uid="T:System.CodeDom.Compiler.ICodeGenerator">
          <source>In the <ph id="ph1">[!INCLUDE[dnprdnlong](~/includes/dnprdnlong-md.md)]</ph>, the <ph id="ph2">&lt;xref:System.CodeDom.Compiler.CodeDomProvider.CreateGenerator%2A&gt;</ph>, <ph id="ph3">&lt;xref:System.CodeDom.Compiler.CodeDomProvider.CreateParser%2A&gt;</ph>, and <ph id="ph4">&lt;xref:System.CodeDom.Compiler.CodeDomProvider.CreateCompiler%2A&gt;</ph> methods are obsolete, and the methods of <ph id="ph5">&lt;xref:System.CodeDom.Compiler.ICodeGenerator&gt;</ph> and <ph id="ph6">&lt;xref:System.CodeDom.Compiler.ICodeCompiler&gt;</ph> are directly available in the <ph id="ph7">&lt;xref:System.CodeDom.Compiler.CodeDomProvider&gt;</ph> class.</source>
          <target state="translated">En el <ph id="ph1">[!INCLUDE[dnprdnlong](~/includes/dnprdnlong-md.md)]</ph>, <ph id="ph2">&lt;xref:System.CodeDom.Compiler.CodeDomProvider.CreateGenerator%2A&gt;</ph>, <ph id="ph3">&lt;xref:System.CodeDom.Compiler.CodeDomProvider.CreateParser%2A&gt;</ph>, y <ph id="ph4">&lt;xref:System.CodeDom.Compiler.CodeDomProvider.CreateCompiler%2A&gt;</ph> métodos están obsoletos y los métodos de <ph id="ph5">&lt;xref:System.CodeDom.Compiler.ICodeGenerator&gt;</ph> y <ph id="ph6">&lt;xref:System.CodeDom.Compiler.ICodeCompiler&gt;</ph> están disponibles directamente en el <ph id="ph7">&lt;xref:System.CodeDom.Compiler.CodeDomProvider&gt;</ph> clase.</target>       </trans-unit>
        <trans-unit id="104" translate="yes" xml:space="preserve" extradata="MT" uid="T:System.CodeDom.Compiler.ICodeGenerator">
          <source>You should override those methods in your code provider implementation and not call the base methods.</source>
          <target state="translated">Debe invalidar estos métodos en su implementación del proveedor de código y no llame a los métodos base.</target>       </trans-unit>
        <trans-unit id="105" translate="yes" xml:space="preserve" extradata="MT" uid="T:System.CodeDom.Compiler.ICodeGenerator">
          <source>Developers of compilers can implement this interface to allow people to dynamically generate code in a particular language.</source>
          <target state="translated">Los programadores de compiladores pueden implementar esta interfaz para permitir a los usuarios generar dinámicamente código en un lenguaje determinado.</target>       </trans-unit>
        <trans-unit id="106" translate="yes" xml:space="preserve" extradata="MT" uid="T:System.CodeDom.Compiler.ICodeGenerator">
          <source>This can be used for a variety of purposes, such as creating code-generating wizards, creating dynamic assemblies with content that can be debugged, and for templated documents with embedded code, such as ASP.NET.</source>
          <target state="translated">Esto puede usarse para una variedad de propósitos, como la creación de asistentes de generación de código, creación de ensamblados dinámicos con contenido que se pueden depurar y para documentos con plantilla con código incrustado, como ASP.NET.</target>       </trans-unit>
        <trans-unit id="107" translate="yes" xml:space="preserve" extradata="MT" uid="T:System.CodeDom.Compiler.ICodeGenerator">
          <source>An <ph id="ph1">&lt;xref:System.CodeDom.Compiler.ICodeGenerator&gt;</ph> implementation is typically obtained through a call to the <ph id="ph2">&lt;xref:System.CodeDom.Compiler.CodeDomProvider.CreateGenerator%2A&gt;</ph> method of <ph id="ph3">&lt;xref:System.CodeDom.Compiler.CodeDomProvider&gt;</ph>.</source>
          <target state="translated">Un <ph id="ph1">&lt;xref:System.CodeDom.Compiler.ICodeGenerator&gt;</ph> implementación normalmente se obtiene a través de una llamada a la <ph id="ph2">&lt;xref:System.CodeDom.Compiler.CodeDomProvider.CreateGenerator%2A&gt;</ph> método <ph id="ph3">&lt;xref:System.CodeDom.Compiler.CodeDomProvider&gt;</ph>.</target>       </trans-unit>
        <trans-unit id="108" translate="yes" xml:space="preserve" uid="M:System.CodeDom.Compiler.ICodeGenerator.CreateEscapedIdentifier(System.String)">
          <source>The string to create an escaped identifier for.</source>
          <target state="translated">Cadena para crear un identificador de escape.</target>       </trans-unit>
        <trans-unit id="109" translate="yes" xml:space="preserve" uid="M:System.CodeDom.Compiler.ICodeGenerator.CreateEscapedIdentifier(System.String)">
          <source>Creates an escaped identifier for the specified value.</source>
          <target state="translated">Crea un identificador de escape para el valor especificado.</target>       </trans-unit>
        <trans-unit id="110" translate="yes" xml:space="preserve" uid="M:System.CodeDom.Compiler.ICodeGenerator.CreateEscapedIdentifier(System.String)">
          <source>The escaped identifier for the value.</source>
          <target state="translated">Identificador de escape para el valor.</target>       </trans-unit>
        <trans-unit id="111" translate="yes" xml:space="preserve" extradata="MT" uid="M:System.CodeDom.Compiler.ICodeGenerator.CreateEscapedIdentifier(System.String)">
          <source><ph id="ph1">&lt;xref:System.CodeDom.Compiler.ICodeGenerator.CreateEscapedIdentifier%2A&gt;</ph> tests whether the identifier conflicts with reserved or language keywords, and if so, returns an equivalent name with language-specific escape code formatting.</source>
          <target state="translated"><ph id="ph1">&lt;xref:System.CodeDom.Compiler.ICodeGenerator.CreateEscapedIdentifier%2A&gt;</ph> comprueba si el identificador entra en conflicto con reservadas o palabras clave del lenguaje y si es así, devuelve un nombre equivalente con formato de código de escape específico del lenguaje.</target>       </trans-unit>
        <trans-unit id="112" translate="yes" xml:space="preserve" extradata="MT" uid="M:System.CodeDom.Compiler.ICodeGenerator.CreateEscapedIdentifier(System.String)">
          <source>This is referred to an escaped identifier.</source>
          <target state="translated">Esto se conoce como identificador de escape.</target>       </trans-unit>
        <trans-unit id="113" translate="yes" xml:space="preserve" extradata="MT" uid="M:System.CodeDom.Compiler.ICodeGenerator.CreateEscapedIdentifier(System.String)">
          <source>The escaped identifier will contain the same <ph id="ph1">`value`</ph> but will have escape code formatting added to differentiate the identifier from the keyword.</source>
          <target state="translated">El identificador de escape contendrá el mismo <ph id="ph1">`value`</ph> , pero tendrá el formato de código de escape agregado para distinguir el identificador de la palabra clave.</target>       </trans-unit>
        <trans-unit id="114" translate="yes" xml:space="preserve" extradata="MT" uid="M:System.CodeDom.Compiler.ICodeGenerator.CreateEscapedIdentifier(System.String)">
          <source>Two implementation examples are preceding the <ph id="ph1">`value`</ph> with "@" or bracketing the <ph id="ph2">`value`</ph> with "[" and "]".</source>
          <target state="translated">Dos ejemplos de implementación preceden la <ph id="ph1">`value`</ph> con "@" o Estimando el <ph id="ph2">`value`</ph> con "[" y "]".</target>       </trans-unit>
        <trans-unit id="115" translate="yes" xml:space="preserve" extradata="MT" uid="M:System.CodeDom.Compiler.ICodeGenerator.CreateEscapedIdentifier(System.String)">
          <source>for full trust for the immediate caller.</source>
          <target state="translated">De plena confianza para el llamador inmediato.</target>       </trans-unit>
        <trans-unit id="116" translate="yes" xml:space="preserve" extradata="MT" uid="M:System.CodeDom.Compiler.ICodeGenerator.CreateEscapedIdentifier(System.String)">
          <source>This member cannot be used by partially trusted code.</source>
          <target state="translated">Un código de confianza parcial no puede utilizar este miembro.</target>       </trans-unit>
        <trans-unit id="117" translate="yes" xml:space="preserve" extradata="MT" uid="M:System.CodeDom.Compiler.ICodeGenerator.CreateEscapedIdentifier(System.String)">
          <source>for full trust for inheritors.</source>
          <target state="translated">de plena confianza para los herederos.</target>       </trans-unit>
        <trans-unit id="118" translate="yes" xml:space="preserve" extradata="MT" uid="M:System.CodeDom.Compiler.ICodeGenerator.CreateEscapedIdentifier(System.String)">
          <source>This member cannot be inherited by partially trusted code.</source>
          <target state="translated">Este miembro no puede heredar código de confianza parcial.</target>       </trans-unit>
        <trans-unit id="119" translate="yes" xml:space="preserve" uid="M:System.CodeDom.Compiler.ICodeGenerator.CreateValidIdentifier(System.String)">
          <source>The string to generate a valid identifier for.</source>
          <target state="translated">Cadena para generar un identificador válido.</target>       </trans-unit>
        <trans-unit id="120" translate="yes" xml:space="preserve" uid="M:System.CodeDom.Compiler.ICodeGenerator.CreateValidIdentifier(System.String)">
          <source>Creates a valid identifier for the specified value.</source>
          <target state="translated">Crea un identificador válido para el valor especificado.</target>       </trans-unit>
        <trans-unit id="121" translate="yes" xml:space="preserve" uid="M:System.CodeDom.Compiler.ICodeGenerator.CreateValidIdentifier(System.String)">
          <source>A valid identifier for the specified value.</source>
          <target state="translated">Identificador válido para el valor especificado.</target>       </trans-unit>
        <trans-unit id="122" translate="yes" xml:space="preserve" extradata="MT" uid="M:System.CodeDom.Compiler.ICodeGenerator.CreateValidIdentifier(System.String)">
          <source><ph id="ph1">&lt;xref:System.CodeDom.Compiler.ICodeGenerator.CreateValidIdentifier%2A&gt;</ph> tests whether the identifier conflicts with reserved or language keywords, and returns a valid identifier name that does not conflict.</source>
          <target state="translated"><ph id="ph1">&lt;xref:System.CodeDom.Compiler.ICodeGenerator.CreateValidIdentifier%2A&gt;</ph> pruebas si el identificador entra en conflicto con reservadas o palabras clave del lenguaje y devuelve un nombre de identificador válido que no están en conflicto.</target>       </trans-unit>
        <trans-unit id="123" translate="yes" xml:space="preserve" extradata="MT" uid="M:System.CodeDom.Compiler.ICodeGenerator.CreateValidIdentifier(System.String)">
          <source>The returned identifier will contain the same <ph id="ph1">`value`</ph> but, if it conflicts with reserved or language keywords, will have escape code formatting added to differentiate the identifier from the keyword.</source>
          <target state="translated">El identificador devuelto contendrá el mismo <ph id="ph1">`value`</ph> pero, si entra en conflicto con reservadas o palabras clave del lenguaje, tendrá formato de código de escape agregado para distinguir el identificador de la palabra clave.</target>       </trans-unit>
        <trans-unit id="124" translate="yes" xml:space="preserve" extradata="MT" uid="M:System.CodeDom.Compiler.ICodeGenerator.CreateValidIdentifier(System.String)">
          <source>Typically, if the value needs modification, value is returned preceded by an underscore "_".</source>
          <target state="translated">Por lo general, si el valor necesita modificación, se devuelve valor precedido por un carácter de subrayado "_".</target>       </trans-unit>
        <trans-unit id="125" translate="yes" xml:space="preserve" extradata="MT" uid="M:System.CodeDom.Compiler.ICodeGenerator.CreateValidIdentifier(System.String)">
          <source>for full trust for the immediate caller.</source>
          <target state="translated">De plena confianza para el llamador inmediato.</target>       </trans-unit>
        <trans-unit id="126" translate="yes" xml:space="preserve" extradata="MT" uid="M:System.CodeDom.Compiler.ICodeGenerator.CreateValidIdentifier(System.String)">
          <source>This member cannot be used by partially trusted code.</source>
          <target state="translated">Un código de confianza parcial no puede utilizar este miembro.</target>       </trans-unit>
        <trans-unit id="127" translate="yes" xml:space="preserve" extradata="MT" uid="M:System.CodeDom.Compiler.ICodeGenerator.CreateValidIdentifier(System.String)">
          <source>for full trust for inheritors.</source>
          <target state="translated">de plena confianza para los herederos.</target>       </trans-unit>
        <trans-unit id="128" translate="yes" xml:space="preserve" extradata="MT" uid="M:System.CodeDom.Compiler.ICodeGenerator.CreateValidIdentifier(System.String)">
          <source>This member cannot be inherited by partially trusted code.</source>
          <target state="translated">Este miembro no puede heredar código de confianza parcial.</target>       </trans-unit>
        <trans-unit id="129" translate="yes" xml:space="preserve" uid="M:System.CodeDom.Compiler.ICodeGenerator.GenerateCodeFromCompileUnit(System.CodeDom.CodeCompileUnit,System.IO.TextWriter,System.CodeDom.Compiler.CodeGeneratorOptions)">
          <source>A <ph id="ph1">&lt;see cref="T:System.CodeDom.CodeCompileUnit" /&gt;</ph> to generate code for.</source>
          <target state="translated"><ph id="ph1">&lt;see cref="T:System.CodeDom.CodeCompileUnit" /&gt;</ph> para el que se va a generar código.</target>       </trans-unit>
        <trans-unit id="130" translate="yes" xml:space="preserve" uid="M:System.CodeDom.Compiler.ICodeGenerator.GenerateCodeFromCompileUnit(System.CodeDom.CodeCompileUnit,System.IO.TextWriter,System.CodeDom.Compiler.CodeGeneratorOptions)">
          <source>The <ph id="ph1">&lt;see cref="T:System.IO.TextWriter" /&gt;</ph> to output code to.</source>
          <target state="translated"><ph id="ph1">&lt;see cref="T:System.IO.TextWriter" /&gt;</ph> al que se envía el código.</target>       </trans-unit>
        <trans-unit id="131" translate="yes" xml:space="preserve" uid="M:System.CodeDom.Compiler.ICodeGenerator.GenerateCodeFromCompileUnit(System.CodeDom.CodeCompileUnit,System.IO.TextWriter,System.CodeDom.Compiler.CodeGeneratorOptions)">
          <source>A <ph id="ph1">&lt;see cref="T:System.CodeDom.Compiler.CodeGeneratorOptions" /&gt;</ph> that indicates the options to use for generating code.</source>
          <target state="translated"><ph id="ph1">&lt;see cref="T:System.CodeDom.Compiler.CodeGeneratorOptions" /&gt;</ph> que indica las opciones que se van a utilizar para generar código.</target>       </trans-unit>
        <trans-unit id="132" translate="yes" xml:space="preserve" uid="M:System.CodeDom.Compiler.ICodeGenerator.GenerateCodeFromCompileUnit(System.CodeDom.CodeCompileUnit,System.IO.TextWriter,System.CodeDom.Compiler.CodeGeneratorOptions)">
          <source>Generates code for the specified Code Document Object Model (CodeDOM) compilation unit and outputs it to the specified text writer using the specified options.</source>
          <target state="translated">Genera código para la unidad de compilación de Code Document Object Model (CodeDOM) especificada y lo envía al escritor de texto especificado mediante las opciones especificadas.</target>       </trans-unit>
        <trans-unit id="133" translate="yes" xml:space="preserve" extradata="MT" uid="M:System.CodeDom.Compiler.ICodeGenerator.GenerateCodeFromCompileUnit(System.CodeDom.CodeCompileUnit,System.IO.TextWriter,System.CodeDom.Compiler.CodeGeneratorOptions)">
          <source>for full trust for the immediate caller.</source>
          <target state="translated">De plena confianza para el llamador inmediato.</target>       </trans-unit>
        <trans-unit id="134" translate="yes" xml:space="preserve" extradata="MT" uid="M:System.CodeDom.Compiler.ICodeGenerator.GenerateCodeFromCompileUnit(System.CodeDom.CodeCompileUnit,System.IO.TextWriter,System.CodeDom.Compiler.CodeGeneratorOptions)">
          <source>This member cannot be used by partially trusted code.</source>
          <target state="translated">Un código de confianza parcial no puede utilizar este miembro.</target>       </trans-unit>
        <trans-unit id="135" translate="yes" xml:space="preserve" extradata="MT" uid="M:System.CodeDom.Compiler.ICodeGenerator.GenerateCodeFromCompileUnit(System.CodeDom.CodeCompileUnit,System.IO.TextWriter,System.CodeDom.Compiler.CodeGeneratorOptions)">
          <source>for full trust for inheritors.</source>
          <target state="translated">de plena confianza para los herederos.</target>       </trans-unit>
        <trans-unit id="136" translate="yes" xml:space="preserve" extradata="MT" uid="M:System.CodeDom.Compiler.ICodeGenerator.GenerateCodeFromCompileUnit(System.CodeDom.CodeCompileUnit,System.IO.TextWriter,System.CodeDom.Compiler.CodeGeneratorOptions)">
          <source>This member cannot be inherited by partially trusted code.</source>
          <target state="translated">Este miembro no puede heredar código de confianza parcial.</target>       </trans-unit>
        <trans-unit id="137" translate="yes" xml:space="preserve" uid="M:System.CodeDom.Compiler.ICodeGenerator.GenerateCodeFromExpression(System.CodeDom.CodeExpression,System.IO.TextWriter,System.CodeDom.Compiler.CodeGeneratorOptions)">
          <source>A <ph id="ph1">&lt;see cref="T:System.CodeDom.CodeExpression" /&gt;</ph> that indicates the expression to generate code for.</source>
          <target state="translated"><ph id="ph1">&lt;see cref="T:System.CodeDom.CodeExpression" /&gt;</ph> que indica la expresión para la que se va a generar código.</target>       </trans-unit>
        <trans-unit id="138" translate="yes" xml:space="preserve" uid="M:System.CodeDom.Compiler.ICodeGenerator.GenerateCodeFromExpression(System.CodeDom.CodeExpression,System.IO.TextWriter,System.CodeDom.Compiler.CodeGeneratorOptions)">
          <source>The <ph id="ph1">&lt;see cref="T:System.IO.TextWriter" /&gt;</ph> to output code to.</source>
          <target state="translated"><ph id="ph1">&lt;see cref="T:System.IO.TextWriter" /&gt;</ph> al que se envía el código.</target>       </trans-unit>
        <trans-unit id="139" translate="yes" xml:space="preserve" uid="M:System.CodeDom.Compiler.ICodeGenerator.GenerateCodeFromExpression(System.CodeDom.CodeExpression,System.IO.TextWriter,System.CodeDom.Compiler.CodeGeneratorOptions)">
          <source>A <ph id="ph1">&lt;see cref="T:System.CodeDom.Compiler.CodeGeneratorOptions" /&gt;</ph> that indicates the options to use for generating code.</source>
          <target state="translated"><ph id="ph1">&lt;see cref="T:System.CodeDom.Compiler.CodeGeneratorOptions" /&gt;</ph> que indica las opciones que se van a utilizar para generar código.</target>       </trans-unit>
        <trans-unit id="140" translate="yes" xml:space="preserve" uid="M:System.CodeDom.Compiler.ICodeGenerator.GenerateCodeFromExpression(System.CodeDom.CodeExpression,System.IO.TextWriter,System.CodeDom.Compiler.CodeGeneratorOptions)">
          <source>Generates code for the specified Code Document Object Model (CodeDOM) expression and outputs it to the specified text writer.</source>
          <target state="translated">Genera código para la expresión de Code Document Object Model (CodeDOM) especificada y lo envía al escritor de texto especificado.</target>       </trans-unit>
        <trans-unit id="141" translate="yes" xml:space="preserve" extradata="MT" uid="M:System.CodeDom.Compiler.ICodeGenerator.GenerateCodeFromExpression(System.CodeDom.CodeExpression,System.IO.TextWriter,System.CodeDom.Compiler.CodeGeneratorOptions)">
          <source>for full trust for the immediate caller.</source>
          <target state="translated">De plena confianza para el llamador inmediato.</target>       </trans-unit>
        <trans-unit id="142" translate="yes" xml:space="preserve" extradata="MT" uid="M:System.CodeDom.Compiler.ICodeGenerator.GenerateCodeFromExpression(System.CodeDom.CodeExpression,System.IO.TextWriter,System.CodeDom.Compiler.CodeGeneratorOptions)">
          <source>This member cannot be used by partially trusted code.</source>
          <target state="translated">Un código de confianza parcial no puede utilizar este miembro.</target>       </trans-unit>
        <trans-unit id="143" translate="yes" xml:space="preserve" extradata="MT" uid="M:System.CodeDom.Compiler.ICodeGenerator.GenerateCodeFromExpression(System.CodeDom.CodeExpression,System.IO.TextWriter,System.CodeDom.Compiler.CodeGeneratorOptions)">
          <source>for full trust for inheritors.</source>
          <target state="translated">de plena confianza para los herederos.</target>       </trans-unit>
        <trans-unit id="144" translate="yes" xml:space="preserve" extradata="MT" uid="M:System.CodeDom.Compiler.ICodeGenerator.GenerateCodeFromExpression(System.CodeDom.CodeExpression,System.IO.TextWriter,System.CodeDom.Compiler.CodeGeneratorOptions)">
          <source>This member cannot be inherited by partially trusted code.</source>
          <target state="translated">Este miembro no puede heredar código de confianza parcial.</target>       </trans-unit>
        <trans-unit id="145" translate="yes" xml:space="preserve" uid="M:System.CodeDom.Compiler.ICodeGenerator.GenerateCodeFromNamespace(System.CodeDom.CodeNamespace,System.IO.TextWriter,System.CodeDom.Compiler.CodeGeneratorOptions)">
          <source>A <ph id="ph1">&lt;see cref="T:System.CodeDom.CodeNamespace" /&gt;</ph> that indicates the namespace to generate code for.</source>
          <target state="translated"><ph id="ph1">&lt;see cref="T:System.CodeDom.CodeNamespace" /&gt;</ph> que indica el espacio de nombres para el que se va a generar código.</target>       </trans-unit>
        <trans-unit id="146" translate="yes" xml:space="preserve" uid="M:System.CodeDom.Compiler.ICodeGenerator.GenerateCodeFromNamespace(System.CodeDom.CodeNamespace,System.IO.TextWriter,System.CodeDom.Compiler.CodeGeneratorOptions)">
          <source>The <ph id="ph1">&lt;see cref="T:System.IO.TextWriter" /&gt;</ph> to output code to.</source>
          <target state="translated"><ph id="ph1">&lt;see cref="T:System.IO.TextWriter" /&gt;</ph> al que se envía el código.</target>       </trans-unit>
        <trans-unit id="147" translate="yes" xml:space="preserve" uid="M:System.CodeDom.Compiler.ICodeGenerator.GenerateCodeFromNamespace(System.CodeDom.CodeNamespace,System.IO.TextWriter,System.CodeDom.Compiler.CodeGeneratorOptions)">
          <source>A <ph id="ph1">&lt;see cref="T:System.CodeDom.Compiler.CodeGeneratorOptions" /&gt;</ph> that indicates the options to use for generating code.</source>
          <target state="translated"><ph id="ph1">&lt;see cref="T:System.CodeDom.Compiler.CodeGeneratorOptions" /&gt;</ph> que indica las opciones que se van a utilizar para generar código.</target>       </trans-unit>
        <trans-unit id="148" translate="yes" xml:space="preserve" uid="M:System.CodeDom.Compiler.ICodeGenerator.GenerateCodeFromNamespace(System.CodeDom.CodeNamespace,System.IO.TextWriter,System.CodeDom.Compiler.CodeGeneratorOptions)">
          <source>Generates code for the specified Code Document Object Model (CodeDOM) namespace and outputs it to the specified text writer using the specified options.</source>
          <target state="translated">Genera código para el espacio de nombres de Code Document Object Model (CodeDOM) especificado y lo envía al escritor de texto especificado mediante las opciones especificadas.</target>       </trans-unit>
        <trans-unit id="149" translate="yes" xml:space="preserve" extradata="MT" uid="M:System.CodeDom.Compiler.ICodeGenerator.GenerateCodeFromNamespace(System.CodeDom.CodeNamespace,System.IO.TextWriter,System.CodeDom.Compiler.CodeGeneratorOptions)">
          <source>for full trust for the immediate caller.</source>
          <target state="translated">De plena confianza para el llamador inmediato.</target>       </trans-unit>
        <trans-unit id="150" translate="yes" xml:space="preserve" extradata="MT" uid="M:System.CodeDom.Compiler.ICodeGenerator.GenerateCodeFromNamespace(System.CodeDom.CodeNamespace,System.IO.TextWriter,System.CodeDom.Compiler.CodeGeneratorOptions)">
          <source>This member cannot be used by partially trusted code.</source>
          <target state="translated">Un código de confianza parcial no puede utilizar este miembro.</target>       </trans-unit>
        <trans-unit id="151" translate="yes" xml:space="preserve" extradata="MT" uid="M:System.CodeDom.Compiler.ICodeGenerator.GenerateCodeFromNamespace(System.CodeDom.CodeNamespace,System.IO.TextWriter,System.CodeDom.Compiler.CodeGeneratorOptions)">
          <source>for full trust for inheritors.</source>
          <target state="translated">de plena confianza para los herederos.</target>       </trans-unit>
        <trans-unit id="152" translate="yes" xml:space="preserve" extradata="MT" uid="M:System.CodeDom.Compiler.ICodeGenerator.GenerateCodeFromNamespace(System.CodeDom.CodeNamespace,System.IO.TextWriter,System.CodeDom.Compiler.CodeGeneratorOptions)">
          <source>This member cannot be inherited by partially trusted code.</source>
          <target state="translated">Este miembro no puede heredar código de confianza parcial.</target>       </trans-unit>
        <trans-unit id="153" translate="yes" xml:space="preserve" uid="M:System.CodeDom.Compiler.ICodeGenerator.GenerateCodeFromStatement(System.CodeDom.CodeStatement,System.IO.TextWriter,System.CodeDom.Compiler.CodeGeneratorOptions)">
          <source>A <ph id="ph1">&lt;see cref="T:System.CodeDom.CodeStatement" /&gt;</ph> containing the CodeDOM elements to translate.</source>
          <target state="translated"><ph id="ph1">&lt;see cref="T:System.CodeDom.CodeStatement" /&gt;</ph> que contiene los elementos CodeDOM que se van a traducir.</target>       </trans-unit>
        <trans-unit id="154" translate="yes" xml:space="preserve" uid="M:System.CodeDom.Compiler.ICodeGenerator.GenerateCodeFromStatement(System.CodeDom.CodeStatement,System.IO.TextWriter,System.CodeDom.Compiler.CodeGeneratorOptions)">
          <source>The <ph id="ph1">&lt;see cref="T:System.IO.TextWriter" /&gt;</ph> to output code to.</source>
          <target state="translated"><ph id="ph1">&lt;see cref="T:System.IO.TextWriter" /&gt;</ph> al que se envía el código.</target>       </trans-unit>
        <trans-unit id="155" translate="yes" xml:space="preserve" uid="M:System.CodeDom.Compiler.ICodeGenerator.GenerateCodeFromStatement(System.CodeDom.CodeStatement,System.IO.TextWriter,System.CodeDom.Compiler.CodeGeneratorOptions)">
          <source>A <ph id="ph1">&lt;see cref="T:System.CodeDom.Compiler.CodeGeneratorOptions" /&gt;</ph> that indicates the options to use for generating code.</source>
          <target state="translated"><ph id="ph1">&lt;see cref="T:System.CodeDom.Compiler.CodeGeneratorOptions" /&gt;</ph> que indica las opciones que se van a utilizar para generar código.</target>       </trans-unit>
        <trans-unit id="156" translate="yes" xml:space="preserve" uid="M:System.CodeDom.Compiler.ICodeGenerator.GenerateCodeFromStatement(System.CodeDom.CodeStatement,System.IO.TextWriter,System.CodeDom.Compiler.CodeGeneratorOptions)">
          <source>Generates code for the specified Code Document Object Model (CodeDOM) statement and outputs it to the specified text writer using the specified options.</source>
          <target state="translated">Genera código para la instrucción de Code Document Object Model (CodeDOM) especificada y lo envía al escritor de texto especificado mediante las opciones especificadas.</target>       </trans-unit>
        <trans-unit id="157" translate="yes" xml:space="preserve" extradata="MT" uid="M:System.CodeDom.Compiler.ICodeGenerator.GenerateCodeFromStatement(System.CodeDom.CodeStatement,System.IO.TextWriter,System.CodeDom.Compiler.CodeGeneratorOptions)">
          <source>for full trust for the immediate caller.</source>
          <target state="translated">De plena confianza para el llamador inmediato.</target>       </trans-unit>
        <trans-unit id="158" translate="yes" xml:space="preserve" extradata="MT" uid="M:System.CodeDom.Compiler.ICodeGenerator.GenerateCodeFromStatement(System.CodeDom.CodeStatement,System.IO.TextWriter,System.CodeDom.Compiler.CodeGeneratorOptions)">
          <source>This member cannot be used by partially trusted code.</source>
          <target state="translated">Un código de confianza parcial no puede utilizar este miembro.</target>       </trans-unit>
        <trans-unit id="159" translate="yes" xml:space="preserve" extradata="MT" uid="M:System.CodeDom.Compiler.ICodeGenerator.GenerateCodeFromStatement(System.CodeDom.CodeStatement,System.IO.TextWriter,System.CodeDom.Compiler.CodeGeneratorOptions)">
          <source>for full trust for inheritors.</source>
          <target state="translated">de plena confianza para los herederos.</target>       </trans-unit>
        <trans-unit id="160" translate="yes" xml:space="preserve" extradata="MT" uid="M:System.CodeDom.Compiler.ICodeGenerator.GenerateCodeFromStatement(System.CodeDom.CodeStatement,System.IO.TextWriter,System.CodeDom.Compiler.CodeGeneratorOptions)">
          <source>This member cannot be inherited by partially trusted code.</source>
          <target state="translated">Este miembro no puede heredar código de confianza parcial.</target>       </trans-unit>
        <trans-unit id="161" translate="yes" xml:space="preserve" uid="M:System.CodeDom.Compiler.ICodeGenerator.GenerateCodeFromType(System.CodeDom.CodeTypeDeclaration,System.IO.TextWriter,System.CodeDom.Compiler.CodeGeneratorOptions)">
          <source>A <ph id="ph1">&lt;see cref="T:System.CodeDom.CodeTypeDeclaration" /&gt;</ph> that indicates the type to generate code for.</source>
          <target state="translated"><ph id="ph1">&lt;see cref="T:System.CodeDom.CodeTypeDeclaration" /&gt;</ph> que indica el tipo para el que se va a generar código.</target>       </trans-unit>
        <trans-unit id="162" translate="yes" xml:space="preserve" uid="M:System.CodeDom.Compiler.ICodeGenerator.GenerateCodeFromType(System.CodeDom.CodeTypeDeclaration,System.IO.TextWriter,System.CodeDom.Compiler.CodeGeneratorOptions)">
          <source>The <ph id="ph1">&lt;see cref="T:System.IO.TextWriter" /&gt;</ph> to output code to.</source>
          <target state="translated"><ph id="ph1">&lt;see cref="T:System.IO.TextWriter" /&gt;</ph> al que se envía el código.</target>       </trans-unit>
        <trans-unit id="163" translate="yes" xml:space="preserve" uid="M:System.CodeDom.Compiler.ICodeGenerator.GenerateCodeFromType(System.CodeDom.CodeTypeDeclaration,System.IO.TextWriter,System.CodeDom.Compiler.CodeGeneratorOptions)">
          <source>A <ph id="ph1">&lt;see cref="T:System.CodeDom.Compiler.CodeGeneratorOptions" /&gt;</ph> that indicates the options to use for generating code.</source>
          <target state="translated"><ph id="ph1">&lt;see cref="T:System.CodeDom.Compiler.CodeGeneratorOptions" /&gt;</ph> que indica las opciones que se van a utilizar para generar código.</target>       </trans-unit>
        <trans-unit id="164" translate="yes" xml:space="preserve" uid="M:System.CodeDom.Compiler.ICodeGenerator.GenerateCodeFromType(System.CodeDom.CodeTypeDeclaration,System.IO.TextWriter,System.CodeDom.Compiler.CodeGeneratorOptions)">
          <source>Generates code for the specified Code Document Object Model (CodeDOM) type declaration and outputs it to the specified text writer using the specified options.</source>
          <target state="translated">Genera código para la declaración de Code Document Object Model (CodeDOM) especificada y lo envía al escritor de texto especificado mediante las opciones especificadas.</target>       </trans-unit>
        <trans-unit id="165" translate="yes" xml:space="preserve" extradata="MT" uid="M:System.CodeDom.Compiler.ICodeGenerator.GenerateCodeFromType(System.CodeDom.CodeTypeDeclaration,System.IO.TextWriter,System.CodeDom.Compiler.CodeGeneratorOptions)">
          <source>for full trust for the immediate caller.</source>
          <target state="translated">De plena confianza para el llamador inmediato.</target>       </trans-unit>
        <trans-unit id="166" translate="yes" xml:space="preserve" extradata="MT" uid="M:System.CodeDom.Compiler.ICodeGenerator.GenerateCodeFromType(System.CodeDom.CodeTypeDeclaration,System.IO.TextWriter,System.CodeDom.Compiler.CodeGeneratorOptions)">
          <source>This member cannot be used by partially trusted code.</source>
          <target state="translated">Un código de confianza parcial no puede utilizar este miembro.</target>       </trans-unit>
        <trans-unit id="167" translate="yes" xml:space="preserve" extradata="MT" uid="M:System.CodeDom.Compiler.ICodeGenerator.GenerateCodeFromType(System.CodeDom.CodeTypeDeclaration,System.IO.TextWriter,System.CodeDom.Compiler.CodeGeneratorOptions)">
          <source>for full trust for inheritors.</source>
          <target state="translated">de plena confianza para los herederos.</target>       </trans-unit>
        <trans-unit id="168" translate="yes" xml:space="preserve" extradata="MT" uid="M:System.CodeDom.Compiler.ICodeGenerator.GenerateCodeFromType(System.CodeDom.CodeTypeDeclaration,System.IO.TextWriter,System.CodeDom.Compiler.CodeGeneratorOptions)">
          <source>This member cannot be inherited by partially trusted code.</source>
          <target state="translated">Este miembro no puede heredar código de confianza parcial.</target>       </trans-unit>
        <trans-unit id="169" translate="yes" xml:space="preserve" uid="M:System.CodeDom.Compiler.ICodeGenerator.GetTypeOutput(System.CodeDom.CodeTypeReference)">
          <source>A <ph id="ph1">&lt;see cref="T:System.CodeDom.CodeTypeReference" /&gt;</ph> that indicates the type to return.</source>
          <target state="translated"><ph id="ph1">&lt;see cref="T:System.CodeDom.CodeTypeReference" /&gt;</ph> que indica el tipo que se va a devolver.</target>       </trans-unit>
        <trans-unit id="170" translate="yes" xml:space="preserve" uid="M:System.CodeDom.Compiler.ICodeGenerator.GetTypeOutput(System.CodeDom.CodeTypeReference)">
          <source>Gets the type indicated by the specified <ph id="ph1">&lt;see cref="T:System.CodeDom.CodeTypeReference" /&gt;</ph>.</source>
          <target state="translated">Obtiene el tipo indicado por el <ph id="ph1">&lt;see cref="T:System.CodeDom.CodeTypeReference" /&gt;</ph> especificado.</target>       </trans-unit>
        <trans-unit id="171" translate="yes" xml:space="preserve" uid="M:System.CodeDom.Compiler.ICodeGenerator.GetTypeOutput(System.CodeDom.CodeTypeReference)">
          <source>A text representation of the specified type for the language this code generator is designed to generate code in.</source>
          <target state="translated">Representación de texto del tipo especificado para el lenguaje para el que se ha diseñado la generación de código de este generador de código.</target>       </trans-unit>
        <trans-unit id="172" translate="yes" xml:space="preserve" uid="M:System.CodeDom.Compiler.ICodeGenerator.GetTypeOutput(System.CodeDom.CodeTypeReference)">
          <source>For example, in Visual Basic, passing in type System.Int32 will return "Integer".</source>
          <target state="translated">Por ejemplo, en Visual Basic, al pasar un tipo System.Int32 se devolverá "Integer".</target>       </trans-unit>
        <trans-unit id="173" translate="yes" xml:space="preserve" extradata="MT" uid="M:System.CodeDom.Compiler.ICodeGenerator.GetTypeOutput(System.CodeDom.CodeTypeReference)">
          <source>for full trust for the immediate caller.</source>
          <target state="translated">De plena confianza para el llamador inmediato.</target>       </trans-unit>
        <trans-unit id="174" translate="yes" xml:space="preserve" extradata="MT" uid="M:System.CodeDom.Compiler.ICodeGenerator.GetTypeOutput(System.CodeDom.CodeTypeReference)">
          <source>This member cannot be used by partially trusted code.</source>
          <target state="translated">Un código de confianza parcial no puede utilizar este miembro.</target>       </trans-unit>
        <trans-unit id="175" translate="yes" xml:space="preserve" extradata="MT" uid="M:System.CodeDom.Compiler.ICodeGenerator.GetTypeOutput(System.CodeDom.CodeTypeReference)">
          <source>for full trust for inheritors.</source>
          <target state="translated">de plena confianza para los herederos.</target>       </trans-unit>
        <trans-unit id="176" translate="yes" xml:space="preserve" extradata="MT" uid="M:System.CodeDom.Compiler.ICodeGenerator.GetTypeOutput(System.CodeDom.CodeTypeReference)">
          <source>This member cannot be inherited by partially trusted code.</source>
          <target state="translated">Este miembro no puede heredar código de confianza parcial.</target>       </trans-unit>
        <trans-unit id="177" translate="yes" xml:space="preserve" uid="M:System.CodeDom.Compiler.ICodeGenerator.IsValidIdentifier(System.String)">
          <source>The value to test for being a valid identifier.</source>
          <target state="translated">Valor que hay que comprobar para ver si es un identificador válido.</target>       </trans-unit>
        <trans-unit id="178" translate="yes" xml:space="preserve" uid="M:System.CodeDom.Compiler.ICodeGenerator.IsValidIdentifier(System.String)">
          <source>Gets a value that indicates whether the specified value is a valid identifier for the current language.</source>
          <target state="translated">Obtiene un valor que indica si el valor especificado es un identificador válido para el lenguaje actual.</target>       </trans-unit>
        <trans-unit id="179" translate="yes" xml:space="preserve" uid="M:System.CodeDom.Compiler.ICodeGenerator.IsValidIdentifier(System.String)">
          <source><ph id="ph1">&lt;see langword="true" /&gt;</ph> if the <ph id="ph2">&lt;paramref name="value" /&gt;</ph> parameter is a valid identifier; otherwise, <ph id="ph3">&lt;see langword="false" /&gt;</ph>.</source>
          <target state="translated">Es <ph id="ph1">&lt;see langword="true" /&gt;</ph> si el parámetro <ph id="ph2">&lt;paramref name="value" /&gt;</ph> es un identificador válido; en caso contrario, es <ph id="ph3">&lt;see langword="false" /&gt;</ph>.</target>       </trans-unit>
        <trans-unit id="180" translate="yes" xml:space="preserve" extradata="MT" uid="M:System.CodeDom.Compiler.ICodeGenerator.IsValidIdentifier(System.String)">
          <source>This method tests whether an identifier is valid.</source>
          <target state="translated">Este método comprueba si un identificador es válido.</target>       </trans-unit>
        <trans-unit id="181" translate="yes" xml:space="preserve" extradata="MT" uid="M:System.CodeDom.Compiler.ICodeGenerator.IsValidIdentifier(System.String)">
          <source>When implementing <ph id="ph1">&lt;xref:System.CodeDom.Compiler.ICodeGenerator.IsValidIdentifier%2A&gt;</ph> in a derived class, design the method to test the value passed to it, and return <ph id="ph2">`true`</ph> only if the value fits the rules of the language and does not conflict with a keyword.</source>
          <target state="translated">Al implementar <ph id="ph1">&lt;xref:System.CodeDom.Compiler.ICodeGenerator.IsValidIdentifier%2A&gt;</ph> en una clase derivada, diseñar el método para probar el valor pasado a él y devolver <ph id="ph2">`true`</ph> sólo si el valor se ajusta a las reglas del lenguaje y no entra en conflicto con una palabra clave.</target>       </trans-unit>
        <trans-unit id="182" translate="yes" xml:space="preserve" extradata="MT" uid="M:System.CodeDom.Compiler.ICodeGenerator.IsValidIdentifier(System.String)">
          <source>for full trust for the immediate caller.</source>
          <target state="translated">De plena confianza para el llamador inmediato.</target>       </trans-unit>
        <trans-unit id="183" translate="yes" xml:space="preserve" extradata="MT" uid="M:System.CodeDom.Compiler.ICodeGenerator.IsValidIdentifier(System.String)">
          <source>This member cannot be used by partially trusted code.</source>
          <target state="translated">Un código de confianza parcial no puede utilizar este miembro.</target>       </trans-unit>
        <trans-unit id="184" translate="yes" xml:space="preserve" extradata="MT" uid="M:System.CodeDom.Compiler.ICodeGenerator.IsValidIdentifier(System.String)">
          <source>for full trust for inheritors.</source>
          <target state="translated">de plena confianza para los herederos.</target>       </trans-unit>
        <trans-unit id="185" translate="yes" xml:space="preserve" extradata="MT" uid="M:System.CodeDom.Compiler.ICodeGenerator.IsValidIdentifier(System.String)">
          <source>This member cannot be inherited by partially trusted code.</source>
          <target state="translated">Este miembro no puede heredar código de confianza parcial.</target>       </trans-unit>
        <trans-unit id="186" translate="yes" xml:space="preserve" uid="M:System.CodeDom.Compiler.ICodeGenerator.Supports(System.CodeDom.Compiler.GeneratorSupport)">
          <source>The capabilities to test the generator for.</source>
          <target state="translated">Características para las que se va a comprobar el generador.</target>       </trans-unit>
        <trans-unit id="187" translate="yes" xml:space="preserve" uid="M:System.CodeDom.Compiler.ICodeGenerator.Supports(System.CodeDom.Compiler.GeneratorSupport)">
          <source>Gets a value indicating whether the generator provides support for the language features represented by the specified <ph id="ph1">&lt;see cref="T:System.CodeDom.Compiler.GeneratorSupport" /&gt;</ph> object.</source>
          <target state="translated">Obtiene un valor que indica si el generador proporciona compatibilidad para las características de lenguaje representadas por el objeto <ph id="ph1">&lt;see cref="T:System.CodeDom.Compiler.GeneratorSupport" /&gt;</ph> especificado.</target>       </trans-unit>
        <trans-unit id="188" translate="yes" xml:space="preserve" uid="M:System.CodeDom.Compiler.ICodeGenerator.Supports(System.CodeDom.Compiler.GeneratorSupport)">
          <source><ph id="ph1">&lt;see langword="true" /&gt;</ph> if the specified capabilities are supported; otherwise, <ph id="ph2">&lt;see langword="false" /&gt;</ph>.</source>
          <target state="translated">Es <ph id="ph1">&lt;see langword="true" /&gt;</ph> si se admiten las funciones especificadas; en caso contrario, es <ph id="ph2">&lt;see langword="false" /&gt;</ph>.</target>       </trans-unit>
        <trans-unit id="189" translate="yes" xml:space="preserve" extradata="MT" uid="M:System.CodeDom.Compiler.ICodeGenerator.Supports(System.CodeDom.Compiler.GeneratorSupport)">
          <source>This method can be called with a number of <ph id="ph1">&lt;xref:System.CodeDom.Compiler.GeneratorSupport&gt;</ph> flags at once to test for a set of capabilities by joining a set of appropriate capability flags together with a binary "Or" operator (&amp;#124;).</source>
          <target state="translated">Puede llamar a este método con un número de <ph id="ph1">&lt;xref:System.CodeDom.Compiler.GeneratorSupport&gt;</ph> marcas al mismo tiempo para comprobar un conjunto de funciones mediante la combinación de un conjunto de indicadores de capacidad apropiados junto con un archivo binario operador "O" (&amp;#124;).</target>       </trans-unit>
        <trans-unit id="190" translate="yes" xml:space="preserve" extradata="MT" uid="M:System.CodeDom.Compiler.ICodeGenerator.Supports(System.CodeDom.Compiler.GeneratorSupport)">
          <source>for full trust for the immediate caller.</source>
          <target state="translated">De plena confianza para el llamador inmediato.</target>       </trans-unit>
        <trans-unit id="191" translate="yes" xml:space="preserve" extradata="MT" uid="M:System.CodeDom.Compiler.ICodeGenerator.Supports(System.CodeDom.Compiler.GeneratorSupport)">
          <source>This member cannot be used by partially trusted code.</source>
          <target state="translated">Un código de confianza parcial no puede utilizar este miembro.</target>       </trans-unit>
        <trans-unit id="192" translate="yes" xml:space="preserve" extradata="MT" uid="M:System.CodeDom.Compiler.ICodeGenerator.Supports(System.CodeDom.Compiler.GeneratorSupport)">
          <source>for full trust for inheritors.</source>
          <target state="translated">de plena confianza para los herederos.</target>       </trans-unit>
        <trans-unit id="193" translate="yes" xml:space="preserve" extradata="MT" uid="M:System.CodeDom.Compiler.ICodeGenerator.Supports(System.CodeDom.Compiler.GeneratorSupport)">
          <source>This member cannot be inherited by partially trusted code.</source>
          <target state="translated">Este miembro no puede heredar código de confianza parcial.</target>       </trans-unit>
        <trans-unit id="194" translate="yes" xml:space="preserve" uid="M:System.CodeDom.Compiler.ICodeGenerator.ValidateIdentifier(System.String)">
          <source>The identifier to validate.</source>
          <target state="translated">El identificador que se debe validar.</target>       </trans-unit>
        <trans-unit id="195" translate="yes" xml:space="preserve" uid="M:System.CodeDom.Compiler.ICodeGenerator.ValidateIdentifier(System.String)">
          <source>Throws an exception if the specified value is not a valid identifier.</source>
          <target state="translated">Provoca una excepción si el valor especificado no es un identificador válido.</target>       </trans-unit>
        <trans-unit id="196" translate="yes" xml:space="preserve" extradata="MT" uid="M:System.CodeDom.Compiler.ICodeGenerator.ValidateIdentifier(System.String)">
          <source>Rather than returning a value, this method throws an exception if the specified identifier is not valid according to the method implementation.</source>
          <target state="translated">En lugar de devolver un valor, este método produce una excepción si el identificador especificado no es válido de acuerdo con la implementación del método.</target>       </trans-unit>
        <trans-unit id="197" translate="yes" xml:space="preserve" extradata="MT" uid="M:System.CodeDom.Compiler.ICodeGenerator.ValidateIdentifier(System.String)">
          <source>Typically, the exception is an <ph id="ph1">&lt;xref:System.ArgumentException&gt;</ph>.</source>
          <target state="translated">Normalmente, la excepción es una <ph id="ph1">&lt;xref:System.ArgumentException&gt;</ph>.</target>       </trans-unit>
        <trans-unit id="198" translate="yes" xml:space="preserve" extradata="MT" uid="M:System.CodeDom.Compiler.ICodeGenerator.ValidateIdentifier(System.String)">
          <source>This method enables a code generator that implements this method to produce an informative error message based upon the value of an invalid identifier.</source>
          <target state="translated">Este método permite a un generador de código que implementa este método para generar un mensaje de error informativo en función del valor de un identificador no válido.</target>       </trans-unit>
        <trans-unit id="199" translate="yes" xml:space="preserve" uid="M:System.CodeDom.Compiler.ICodeGenerator.ValidateIdentifier(System.String)">
          <source>The identifier is not valid.</source>
          <target state="translated">El identificador no es válido.</target>       </trans-unit>
        <trans-unit id="200" translate="yes" xml:space="preserve" extradata="MT" uid="M:System.CodeDom.Compiler.ICodeGenerator.ValidateIdentifier(System.String)">
          <source>for full trust for the immediate caller.</source>
          <target state="translated">De plena confianza para el llamador inmediato.</target>       </trans-unit>
        <trans-unit id="201" translate="yes" xml:space="preserve" extradata="MT" uid="M:System.CodeDom.Compiler.ICodeGenerator.ValidateIdentifier(System.String)">
          <source>This member cannot be used by partially trusted code.</source>
          <target state="translated">Un código de confianza parcial no puede utilizar este miembro.</target>       </trans-unit>
        <trans-unit id="202" translate="yes" xml:space="preserve" extradata="MT" uid="M:System.CodeDom.Compiler.ICodeGenerator.ValidateIdentifier(System.String)">
          <source>for full trust for inheritors.</source>
          <target state="translated">de plena confianza para los herederos.</target>       </trans-unit>
        <trans-unit id="203" translate="yes" xml:space="preserve" extradata="MT" uid="M:System.CodeDom.Compiler.ICodeGenerator.ValidateIdentifier(System.String)">
          <source>This member cannot be inherited by partially trusted code.</source>
          <target state="translated">Este miembro no puede heredar código de confianza parcial.</target>       </trans-unit>
      </group>
    </body>
  </file>
</xliff>